magen_test_utils-1.0a1.dist-info/DESCRIPTION.rst
magen_test_utils-1.0a1.dist-info/METADATA
magen_test_utils-1.0a1.dist-info/RECORD
magen_test_utils-1.0a1.dist-info/WHEEL
magen_test_utils-1.0a1.dist-info/metadata.json
magen_test_utils-1.0a1.dist-info/top_level.txt
magen_test_utils_apis/__init__.py
magen_test_utils_apis/test_magen_object_apis.py
